<?xml version="1.0" encoding="utf-8"?>
  <?xml-stylesheet type="text/xsl" href="rfc2629.xslt" ?>
  <!-- generated by https://github.com/cabo/kramdown-rfc2629 version 1.4.19 -->

<!DOCTYPE rfc SYSTEM "rfc2629.dtd" [
]>

<?rfc toc="yes"?>
<?rfc sortrefs="yes"?>
<?rfc symrefs="yes"?>
<?rfc comments="yes"?>

<rfc ipr="trust200902" docName="draft-liu-teas-transport-network-slice-yang-06" category="std">

  <front>
    <title abbrev="Network Slice Topology Data Model">IETF Network Slice Topology YANG Data Model</title>

    <author initials="X." surname="Liu" fullname="Xufeng Liu">
      <organization>IBM Corporation</organization>
      <address>
        <email>xufeng.liu.ietf@gmail.com</email>
      </address>
    </author>
    <author initials="J." surname="Tantsura" fullname="Jeff Tantsura">
      <organization>Microsoft</organization>
      <address>
        <email>jefftant.ietf@gmail.com</email>
      </address>
    </author>
    <author initials="I." surname="Bryskin" fullname="Igor Bryskin">
      <organization>Individual</organization>
      <address>
        <email>i_bryskin@yahoo.com</email>
      </address>
    </author>
    <author initials="L.M." surname="Contreras" fullname="Luis M. Contreras">
      <organization>Telefonica</organization>
      <address>
        <email>luismiguel.contrerasmurillo@telefonica.com</email>
      </address>
    </author>
    <author initials="Q." surname="Wu" fullname="Qin Wu">
      <organization>Huawei</organization>
      <address>
        <email>bill.wu@huawei.com</email>
      </address>
    </author>
    <author initials="S." surname="Belotti" fullname="Sergio Belotti">
      <organization>Nokia</organization>
      <address>
        <email>Sergio.belotti@nokia.com</email>
      </address>
    </author>
    <author initials="R." surname="Rokui" fullname="Reza Rokui">
      <organization>Ciena</organization>
      <address>
        <email>rrokui@ciena.com</email>
      </address>
    </author>
    <author initials="A." surname="Guo" fullname="Aihua Guo">
      <organization>Futurewei</organization>
      <address>
        <email>aihuaguo.ietf@gmail.com</email>
      </address>
    </author>
    <author initials="I." surname="Busi" fullname="Italo Busi">
      <organization>Huawei</organization>
      <address>
        <email>italo.busi@huawei.com</email>
      </address>
    </author>

    <date year="2023" month="February" day="17"/>

    
    <workgroup>TEAS Working Group</workgroup>
    

    <abstract>


<t>An IETF network slice may use an abstract topology to describe intended 
   underlay for connectivities between slice endpoints. Abstract topologies
   help the customer to configure network slices with shared resources
   amongst connections, and connections can be activated within the slice
   as needed.</t>

<t>This document describes a YANG data model for managing and
   controlling abstract topologies for IETF network slices defined in
   <xref target="I-D.ietf-teas-ietf-network-slices"/>.</t>



    </abstract>


  </front>

  <middle>


<section anchor="introduction"><name>Introduction</name>

<t>This document defines a YANG <xref target="RFC7950"/> data model for representing,
   managing, and controlling IETF network slices as abstract
   network topologies, where the network slices are defined
   in <xref target="I-D.ietf-teas-ietf-network-slices"/>.</t>

<t>The defined data model is an interface between customers and
   providers for configurations and state retrievals, so as to support
   network slicing as a service.  Through this model, a customer can
   learn the slicing capabilities and the available resources of the
   provider.  A customer can request or negotiate with a network slicing
   provider to create an instance.  The customer can incrementally
   update its requirements on individual topology elements in the slice
   instance, e.g., adding or removing a node or link, updating desired
   bandwidth of a link, and retrieve the operational states of these elements.
   With the help of other mechanisms and data models defined in IETF,
   the telemetry information can be published to the customer.</t>

<t>The YANG model defines technology-agnostic constructs common to network slicing
   at network layers of different technologies, e.g. IP/MPLS(-TP), OTN and WDM.
   Therefore, this model may be used as a common base model on which other
   network slicing models, such as <xref target="I-D.ietf-ccamp-yang-otn-slicing"/>, may
   augments with technology-specific constructs.</t>

<t>As described in Section 3 of
   <xref target="I-D.contreras-teas-slice-controller-models"/>, the data model defined
   in this document complements the data model defined in
   <xref target="I-D.ietf-teas-ietf-network-slice-nbi-yang"/>.  In addition to the
   provider's view, the data model defined in this document models the
   Type 2 service defined in <xref target="RFC8453"/>.</t>

<t>The YANG data model in this document conforms to the Network
   Management Datastore Architecture (NMDA) <xref target="RFC8342"/>.</t>

<section anchor="terminology"><name>Terminology</name>

<t>The key words "MUST", "MUST NOT", "REQUIRED", "SHALL", "SHALL NOT",
   "SHOULD", "SHOULD NOT", "RECOMMENDED", "NOT RECOMMENDED", "MAY", and
   "OPTIONAL" in this document are to be interpreted as described in
   BCP 14 <xref target="RFC2119"/> <xref target="RFC8174"/> when, and only when, they appear in all
   capitals, as shown here.</t>

<t>The terminology for describing YANG data models is found in
   <xref target="RFC7950"/>.</t>

</section>
<section anchor="tree-diagram"><name>Tree Diagram</name>

<t>Tree diagrams used in this document follow the notation defined in
   <xref target="RFC8340"/>.</t>

</section>
<section anchor="prefixes-in-data-node-names"><name>Prefixes in Data Node Names</name>

<t>In this document, names of data nodes and other data model objects
   are prefixed using the standard prefix associated with the
   corresponding YANG imported modules, as shown in <xref target="tab-prefixes"/>.</t>

<texttable title="Prefixes and Corresponding YANG Modules" anchor="tab-prefixes">
      <ttcol align='left'>Prefix</ttcol>
      <ttcol align='left'>YANG Module</ttcol>
      <ttcol align='left'>Reference</ttcol>
      <c>yang</c>
      <c>ietf-yang-types</c>
      <c><xref target="RFC6991"/></c>
      <c>inet</c>
      <c>ietf-inet-types</c>
      <c><xref target="RFC6991"/></c>
      <c>nt</c>
      <c>ietf-network-topology</c>
      <c><xref target="RFC8345"/></c>
      <c>nw</c>
      <c>ietf-network-topology</c>
      <c><xref target="RFC8345"/></c>
      <c>tet</c>
      <c>ietf-te-topology</c>
      <c><xref target="RFC8795"/></c>
      <c>te-types</c>
      <c>ietf-te-types</c>
      <c><xref target="RFC8776"/></c>
      <c>ns-topo</c>
      <c>ietf-ns-topo</c>
      <c>RFCXXXX</c>
</texttable>

<t>RFC Editor Note:
Please replace XXXX with the RFC number assigned to this document.
Please remove this note.</t>

</section>
</section>
<section anchor="modeling-considerations"><name>Modeling Considerations</name>

<t>An IETF network slice is modeled as network topology defined in
   <xref target="RFC8345"/>, with augmentations.  A new network type "network-slice" is
   defined in this document.  When a network topology data instance
   contains the network-slice network type, it represents an instance of
   an IETF network slice topology.</t>

<section anchor="relationships-to-related-topology-models"><name>Relationships to Related Topology Models</name>

<t>There are several related YANG data models that have been defined in
   IETF.  Some of these are:</t>

<t>Network Topology Model:
      Defined in <xref target="RFC8345"/>.</t>

<t>Network Slicing Model:
      Defined in <xref target="I-D.ietf-teas-ietf-network-slice-nbi-yang"/>.</t>

<t>OTN Slicing:
      Defined in <xref target="I-D.ietf-ccamp-yang-otn-slicing"/>.</t>

<t><xref target="fig-model-relationship"/> shows the relationships among these models.  The box of
   dotted lines denotes the model defined in this document.</t>

<figure title="Model Relationships" anchor="fig-model-relationship"><artwork><![CDATA[
     +----------+                 +----------+
     | Network  |                 | Network  |
     | Slice    |                 | Topology +
     | NBI YANG >------+          | Model    |
     | Model    |      |          | RFC 8345 |
     +----+-----+      |          +-----+----+
          |            |                |
          |augments    |references      |augments
          |            |                |
     +----^-----+      |          ......^.....
     | OTN      |      +----------: Network  :
     | Slicing  | augments        : Slice    :
     | Model    >-----------------: Topology :
     |          |                 : Model    :
     +----------+                 ''''''''''''
]]></artwork></figure>

</section>
<section anchor="actn-for-network-slicing"><name>ACTN for Network Slicing</name>

<t>Since ACTN topology data models are based on the network topology
   model defined in <xref target="RFC8345"/>, the augmentations defined in this
   document are effective augmentations to the ACTN topology data
   models, resulting in making the ACTN framework <xref target="RFC8453"/> and data
   models <xref target="I-D.ietf-teas-actn-yang"/> capable of slicing networks with the
   required network characteristics.</t>

</section>
</section>
<section anchor="model-applicability"><name>Model Applicability</name>

<t>There are many technologies to achieve network slicing.  The data
   model defined in this document can be used to configure resource-based
   network slices, where the resources of a network slice is represented
   in the form of an abstract network topology, which can then be mapped
   to a network resource partition (NRP) according to the scenarios defined
   in <xref target="I-D.ietf-teas-ietf-network-slices"/>.</t>

<t>In the example shown in <xref target="fig-ns-topo-example"/>, node virtualization is used to
   separate and allocate resources in physical devices.  Two virtual
   routers VR1 and VR2 are created over physical router R1, and two virtual
   routers VR3 and VR4 are created over physical router R2, respectively.  Each of the
   virtual routers,as a partition of the physical router, takes a portion 
   of the resources such as ports and memory in the physical router.<br />
   Depending on the requirements and the implementations, they may share 
   certain resources such as processors, ASICs, and switch fabric.</t>

<t>As an example, Appendix B. shows the JSON encoded data instances of
   the native topology and the customized topology for Network Slice
   Blue.</t>

<figure title="Network Slicing Topologies for Virtualization" anchor="fig-ns-topo-example"><artwork><![CDATA[
       Customer Topology                   Customer Topology
       Network Slice Blue                  Network Slice Red
                            +---+         +---+      +---+
                       -----|R3 |---   ---|R2 |------|R3 |
                      /     +---+         +---+      +---+                  
      +---+      +---+                                    \     +---+
   ---|R1 |------|R2 |                                     -----|R4 |---
      +---+      +---+                                          +---+

                                 Customers
   ---------------------------------------------------------------------
                                 Provider

        Customized Topology (Network Resouce Partions)
        Provider Network with Virtual Devices

        Network Slice Blue: VR1, VR3, VR5         +---+             
                                        ----------|VR5|------
                                       /          +---+
                    +---+         +---+
              ------|VR1|---------|VR3|                              
                    +---+         +---+
              ------|VR2|---------|VR4|
                    +---+         +---+
                                       \          +---+
                                        ----------|VR6|------
        Network Slice Red: VR2, VR4, VR6          +---+

                                 Virtual Devices 
   ---------------------------------------------------------------------
                                 Physical Devices

        Native Topology
        Provider Network with Physical Devices
                                                  +---+
                                        ----------|R3 |------
                                       /          +---+
                    +---+         +---+
              ======|R1 |=========|R2 |                             
                    +---+         +---+
                                       \          +---+
                                        ----------|R4 |------
                                                  +---+
]]></artwork></figure>

</section>
<section anchor="yang-model-overview"><name>YANG Model Overview</name>
<t>The following constructs and attributes are defined within the YANG model:</t>

<t><list style="symbols">
  <t>Common attributes, which include a set of common attributes like slice identifier,
name, description, and names of customers who use the slice.</t>
  <t>Endpoints, which represent conceptual points of connection from a customer
device to the TNS. An endpoint is mapped to specific physical or virtual resources
 of the customer and provider, and such mapping is pre-negotiated and known to 
 both the customer and provider prior to the slice configuration. The mechanism 
 for endpoint negotiation is outside the scope of this draft.</t>
  <t>Network topology, which represent set of shared, reserved resources organized as a virtual 
 topology between all of the endpoints. A customer could use such network topology
 to define detailed connectivity path traversing the topology, and allow sharing of 
 resources between its multiple endpoint pairs.</t>
  <t>Connectivity matrix, which represent the intended virtual connections between the endpoints
 within a TNS. A connectivity matrix entry could be associated with an explicit path 
 over the above network topology.</t>
  <t>Service-level objectives (SLOs) associated with different objects, including the TNS, 
 node, link, termination point, and explicit path, within a TNS.</t>
</list></t>

</section>
<section anchor="model-tree-structure"><name>Model Tree Structure</name>

<figure title="Tree diagram for network slice topology" anchor="fig-ietf-ns-topo-tree"><artwork><![CDATA[
module: ietf-ns-topo

  augment /nw:networks/nw:network/nw:network-types:
    +--rw network-slice!
  augment /nw:networks/nw:network:
    +--rw (slo-sle-policy)?
       +--:(standard)
       |  +--rw slo-sle-template?         leafref
       +--:(custom)
          +--rw service-slo-sle-policy
             +--rw policy-description?       string
             +--rw metric-bounds
             |  +--rw metric-bound* [metric-type]
             |     +--rw metric-type          identityref
             |     +--rw metric-unit          string
             |     +--rw value-description?   string
             |     +--rw bound?               uint64
             +--rw security*                 identityref
             +--rw isolation?                identityref
             +--rw max-occupancy-level?      uint8
             +--rw mtu?                      uint16
             +--rw steering-constraints
             |  +--rw path-constraints
             |  +--rw service-function
             |  +--rw disjointness?
             |  |       te-types:te-path-disjointness
             |  +--rw service-info?       string
             +--rw optimization-criterion?   identityref
             +--rw delay-tolerance?          boolean
             +--rw periodicity*              uint64
             +--rw resize-requirement?       identityref
             +--rw service-info?             string
  augment /nw:networks/nw:network/nw:node:
    +--rw (slo-sle-policy)?
       +--:(standard)
       |  +--rw slo-sle-template?         leafref
       +--:(custom)
          +--rw service-slo-sle-policy
             +--rw policy-description?       string
             +--rw metric-bounds
             |  +--rw metric-bound* [metric-type]
             |     +--rw metric-type          identityref
             |     +--rw metric-unit          string
             |     +--rw value-description?   string
             |     +--rw bound?               uint64
             +--rw security*                 identityref
             +--rw isolation?                identityref
             +--rw max-occupancy-level?      uint8
             +--rw mtu?                      uint16
             +--rw steering-constraints
             |  +--rw path-constraints
             |  +--rw service-function
             +--rw optimization-criterion?   identityref
             +--rw delay-tolerance?          boolean
             +--rw periodicity*              uint64
             +--rw resize-requirement?       identityref
             +--rw service-info?             string
  augment /nw:networks/nw:network/nw:node/nt:termination-point:
    +--rw customer-facing-sdp-id?         leafref
    +--rw (slo-sle-policy)?
       +--:(standard)
       |  +--rw slo-sle-template?         leafref
       +--:(custom)
          +--rw service-slo-sle-policy
             +--rw policy-description?       string
             +--rw metric-bounds
             |  +--rw metric-bound* [metric-type]
             |     +--rw metric-type          identityref
             |     +--rw metric-unit          string
             |     +--rw value-description?   string
             |     +--rw bound?               uint64
             +--rw security*                 identityref
             +--rw isolation?                identityref
             +--rw max-occupancy-level?      uint8
             +--rw mtu?                      uint16
             +--rw steering-constraints
             |  +--rw path-constraints
             |  +--rw service-function
             +--rw optimization-criterion?   identityref
             +--rw delay-tolerance?          boolean
             +--rw periodicity*              uint64
             +--rw resize-requirement?       identityref
             +--rw service-info?             string
  augment /nw:networks/nw:network/nt:link:
    +--rw (slo-sle-policy)?
    |  +--:(standard)
    |  |  +--rw slo-sle-template?         leafref
    |  +--:(custom)
    |     +--rw service-slo-sle-policy
    |        +--rw policy-description?       string
    |        +--rw metric-bounds
    |        |  +--rw metric-bound* [metric-type]
    |        |     +--rw metric-type          identityref
    |        |     +--rw metric-unit          string
    |        |     +--rw value-description?   string
    |        |     +--rw bound?               uint64
    |        +--rw security*                 identityref
    |        +--rw isolation?                identityref
    |        +--rw max-occupancy-level?      uint8
    |        +--rw mtu?                      uint16
    |        +--rw steering-constraints
    |        |  +--rw path-constraints
    |        |  +--rw service-function
    |        |  +--rw disjointness?
    |        |  |       te-types:te-path-disjointness
    |        |  +--rw service-info?       string
    |        +--rw optimization-criterion?   identityref
    |        +--rw delay-tolerance?          boolean
    |        +--rw periodicity*              uint64
    |        +--rw resize-requirement?       identityref
    |        +--rw service-info?             string
    +--rw optimization-criterion?         identityref
    +--rw delay-tolerance?                boolean
    +--rw periodicity*                    uint64
    +--rw resize-requirement?             identityref
    +--rw service-info?                   string
]]></artwork></figure>

</section>
<section anchor="yang-modules"><name>YANG Modules</name>

<figure title="YANG model for network slice topology" anchor="fig-ietf-ns-topo-yang"><artwork><![CDATA[
   <CODE BEGINS> file "ietf-ns-topo@2023-01-31.yang"
   module ietf-ns-topo {
     yang-version 1.1;
     namespace
       "urn:ietf:params:xml:ns:yang:ietf-ns-topo";
     prefix "ns-topo";

     import ietf-network {
       prefix "nw";
       reference "RFC 8345: A YANG Data Model for Network Topologies";
     }
     import ietf-network-topology {
       prefix "nt";
       reference "RFC 8345: A YANG Data Model for Network Topologies";
     }

     import ietf-te-types {
       prefix "te-types";
       reference
         "RFC 8776: Traffic Engineering Common YANG Types";
     }

     import ietf-network-slice-service {
       prefix "ietf-nss";
       reference
         "draft-ietf-teas-ietf-network-slice-nbi-yang-00:
          IETF Network Slice Service YANG Model";
     }
 
     organization
       "IETF CCAMP Working Group";
     contact
       "WG Web: <http://tools.ietf.org/wg/ccamp/>
        WG List: <mailto:ccamp@ietf.org>

        Editor: Xufeng Liu
                <mailto:xufeng.liu.ietf@gmail.com>

        Editor: Italo Busi
                <mailto:italo.busi@huawei.com>

        Editor: Aihua Guo
                <mailto:aihuaguo.ietf@gmail.com>

        Editor: Sergio Belotti
                <mailto:sergio.belotti@nokia.com>

        Editor: Luis M. Contreras
                <mailto:luismiguel.contrerasmurillo@telefonica.com>";

     description
       "This module defines a base YANG data model for configuring
        generic network slices in optical transport networks, e.g.,
        Optical Transport Network (OTN).

        The model fully conforms to the Network Management Datastore
        Architecture (NMDA).

        Copyright (c) 2023 IETF Trust and the persons identified as
        authors of the code.  All rights reserved.

        Redistribution and use in source and binary forms, with or
        without modification, is permitted pursuant to, and subject
        to the license terms contained in, the Revised BSD License
        set forth in Section 4.c of the IETF Trust's Legal Provisions
        Relating to IETF Documents
        (https://trustee.ietf.org/license-info).

        This version of this YANG module is part of RFC XXXX; see the
        RFC itself for full legal notices.";

     revision 2023-02-08 {
       description "Initial revision";
       reference
         "RFC XXXX: IETF Network Slice Topology YANG Data Model";
     }

     /*
      * Identities
      */
     identity isolation-level {
       description
         "Base identity for the isolation-level.";
       reference
         "GSMA-NS-Template: Generic Network Slice Template,
          Version 3.0.";
     }
     identity no-isolation {
       base isolation-level;
       description
         "Network slices are not separated.";
     }
     identity physical-isolation {
       base isolation-level;
       description
         "Network slices are physically separated (e.g. different
          rack, different hardware, different location, etc.).";
     }
     identity logical-isolation {
       base isolation-level;
       description
         "Network slices are logically separated.";
     }
     identity process-isolation {
       base physical-isolation;
       description
         "Process and threads isolation.";
     }
     identity physical-memory-isolation {
       base physical-isolation;
       description
         "Process and threads isolation.";
     }
     identity physical-network-isolation {
       base physical-isolation;
       description
         "Process and threads isolation.";
     }
     identity virtual-resource-isolation {
       base logical-isolation;
       description
         "A network slice has access to specific range of resources
          that do not overlap with other network slices
          (e.g. VM isolation).";
     }
     identity network-functions-isolation {
       base logical-isolation;
       description
         "NF (Network Function) is dedicated to the network slice,
          but virtual resources are shared.";
     }
     identity service-isolation {
       base logical-isolation;
       description
         "NSC data are isolated from other NSCs, but virtual
          resources and NFs are shared.";
     }

     identity resize-option {
       description
         "Base identity for link or connectivity resizing options";
     }
 
     identity resize-none {
       base resize-option;
       description
         "Not resizable";
     }
 
     identity resize-with-hit {
       base resize-option;
       description
         "Resizable with traffic hits";
     }

     identity resize-hitless {
       base resize-option;
       description
         "Hitless resizable";
     }
 
     /*
      * Groupings
      */

     grouping ns-topo-slo-sle-policy {
       description
         "Policy grouping for Transport Network Slices.";

       leaf optimization-criterion {
           type identityref {
             base te-types:objective-function-type;
           }
           description
             "Optimization criterion applied to this topology.";
       }
       leaf delay-tolerance {
         type boolean;
         description
           "'true' if is not too critical how long it takes to
            deliver the amount of data.";
         reference
           "GSMA-NS-Template: Generic Network Slice Template,
            Version 3.0.";
       }
       leaf-list periodicity {
         type uint64;
         units seconds;
         description
           "A list of periodicities supported by the network
            slice.";
         reference
           "GSMA-NS-Template: Generic Network Slice Template,
            Version 3.0.";
       }
       leaf resize-requirement {
         type identityref {
           base resize-option;
         }
         description
           "Indicates resizing requirments";
       }
       leaf service-info {
         type string;
         description
           "Describe type of services running on the slice. It may be
            useful information to help the slice controller to 
            optimize resource allocation";
       }
     }
         
     grouping ns-topo-steering-constraints {
       description
         "Policy grouping for specifying steering constraints for
          Transport Network Slices.";

       leaf disjointness {
         type te-types:te-path-disjointness;
         description
           "Indicate the level of disjointness for slice
            resources.";
       }
       leaf service-info {
         type string;
         description
           "Describe type of services running on the slice. It may be
            useful information to help the slice controller to 
            optimize resource allocation";
       }
     }

     /*
      * Augmented data nodes
      */
     /* network type augments */
     augment "/nw:networks/nw:network/nw:network-types" {
       description
         "Defines the Network Slice topology type.";
       container network-slice {
         presence "Indicates Network Slice topology";
         description
           "Its presence identifies the Network Slice type.";
       }
     }
     
     /* network topology augments */
     augment "/nw:networks/nw:network" {
       when "./nw:network-types/ns-topo:network-slice" {
         description "Augment only for Network Slice topology.";
       }
       description "Augment topology configuration and state.";
       uses ietf-nss:service-slo-sle-policy;
     }

     augment "/nw:networks/nw:network" +
             "/ns-topo:slo-sle-policy" +
             "/ns-topo:custom" +
             "/ns-topo:service-slo-sle-policy" {
       when "../nw:network-types/ns-topo:network-slice" {
         description "Augment only for Network Slice topology.";
       }
       description "Augment topology configuration and state.";
       uses ns-topo-slo-sle-policy;
     }

     augment "/nw:networks/nw:network" +
             "/ns-topo:slo-sle-policy" +
             "/ns-topo:custom" +
             "/ns-topo:service-slo-sle-policy" +
                         "/ns-topo:steering-constraints" {
       when "../../nw:network-types/ns-topo:network-slice" {
         description "Augment only for Network Slice topology.";
       }
       description "Augment topology configuration and state.";
       uses ns-topo-steering-constraints;
     }

     /* network node augments */
     augment "/nw:networks/nw:network/nw:node" {
       when "../nw:network-types/ns-topo:network-slice" {
         description "Augment only for Network Slice topology.";
       }
       description "Augment node configuration and state.";
       uses ietf-nss:service-slo-sle-policy;
     }

     augment "/nw:networks/nw:network/nw:node" +
             "/ns-topo:slo-sle-policy" + 
             "/ns-topo:custom" + 
             "/ns-topo:service-slo-sle-policy" {
       when "../../nw:network-types/ns-topo:network-slice" {
         description "Augment only for Network Slice topology.";
       }
       description "Augment node configuration and state.";
       uses ns-topo-slo-sle-policy;
     }

     /* network node's termination point augments */
     augment "/nw:networks/nw:network/nw:node" +
             "/nt:termination-point" {
       when "../../nw:network-types/ns-topo:network-slice" {
         description "Augment only for Network Slice topology.";
       }
       description "Augment node configuration and state.";
           
       leaf customer-facing-sdp-id {
                 type leafref {
                   path "/ietf-nss:network-slice-services"+
                                "/ietf-nss:slice-service"+
                                "/ietf-nss:sdps/ietf-nss:sdp/ietf-nss:sdp-id";
                 }
                 description
                   "Relative reference to a customer-facing SDP.";
           }

           uses ietf-nss:service-slo-sle-policy;
     }
         
     augment "/nw:networks/nw:network/nw:node" +
             "/nt:termination-point" +
             "/ns-topo:slo-sle-policy" + 
             "/ns-topo:custom" + 
             "/ns-topo:service-slo-sle-policy" {
       when "../../../nw:network-types/ns-topo:network-slice" {
         description "Augment only for Network Slice topology.";
       }
       description "Augment node configuration and state.";
           
       uses ns-topo-slo-sle-policy;
     }

     /* network link augments */
     augment "/nw:networks/nw:network/nt:link" {
       when "../nw:network-types/ns-topo:network-slice" {
         description "Augment only for Network Slice topology.";
       }
       description "Augment link configuration and state.";
       uses ietf-nss:service-slo-sle-policy;
           uses ns-topo-slo-sle-policy;
     }

     augment "/nw:networks/nw:network/nt:link" +
             "/ns-topo:slo-sle-policy" + 
             "/ns-topo:custom" + 
             "/ns-topo:service-slo-sle-policy" {
       when "../../nw:network-types/ns-topo:network-slice" {
         description "Augment only for Network Slice topology.";
       }
       description "Augment link configuration and state.";
       uses ns-topo-slo-sle-policy;
     }

     augment "/nw:networks/nw:network/nt:link" +
             "/ns-topo:slo-sle-policy" + 
             "/ns-topo:custom" + 
             "/ns-topo:service-slo-sle-policy" + 
             "/ns-topo:steering-constraints" {
       when "../../../nw:network-types/ns-topo:network-slice" {
         description "Augment only for Network Slice topology.";
       }
       description
             "Augment IETF network slice services to include steering
          constraints for links within a resource-based transport
          network slice.";
       uses ns-topo-steering-constraints;
     }
   }
   <CODE ENDS>
]]></artwork></figure>

</section>
<section anchor="manageability-considerations"><name>Manageability Considerations</name>

<t>To ensure the security and controllability of physical resource
   isolation, slice-based independent operation and management are
   required to achieve management isolation.
   Each optical slice typically requires dedicated accounts,
   permissions, and resources for independent access and O&amp;M. This
   mechanism is to guarantee the information isolation among slice
   tenants and to avoid resource conflicts. The access to slice
   management functions will only be permitted after successful security
   checks.</t>

</section>
<section anchor="security-considerations"><name>Security Considerations</name>

<t>The YANG module specified in this document defines a schema for data
   that is designed to be accessed via network management protocols such
   as NETCONF <xref target="RFC6241"/> or RESTCONF <xref target="RFC8040"/>.  The lowest NETCONF layer
   is the secure transport layer, and the mandatory-to-implement secure
   transport is Secure Shell (SSH) <xref target="RFC6242"/>.  The lowest RESTCONF layer
   is HTTPS, and the mandatory-to-implement secure transport is TLS
   <xref target="RFC8446"/>.</t>

<t>The NETCONF access control model <xref target="RFC8341"/> provides the means to
   restrict access for particular NETCONF or RESTCONF users to a
   preconfigured subset of all available NETCONF or RESTCONF protocol
   operations and content.</t>

<t>There are a number of data nodes defined in this YANG module that are
   writable/creatable/deletable (i.e., config true, which is the
   default).  These data nodes may be considered sensitive or vulnerable
   in some network environments.  Write operations (e.g., edit-config)
   to these data nodes without proper protection can have a negative
   effect on network operations.  Considerations in Section 8 of
   <xref target="RFC8795"/> are also applicable to their subtrees in the module defined
   in this document.</t>

<t>Some of the readable data nodes in this YANG module may be considered
   sensitive or vulnerable in some network environments.  It is thus
   important to control read access (e.g., via get, get-config, or
   notification) to these data nodes.  Considerations in Section 8 of
   <xref target="RFC8795"/> are also applicable to their subtrees in the module defined
   in this document.</t>

</section>
<section anchor="iana-considerations"><name>IANA Considerations</name>

<t>It is proposed to IANA to assign new URIs from the "IETF XML
   Registry" <xref target="RFC3688"/> as follows:</t>

<figure><artwork><![CDATA[
   URI: urn:ietf:params:xml:ns:yang:ietf-ns-topo
   Registrant Contact: The IESG
   XML: N/A; the requested URI is an XML namespace.
]]></artwork></figure>

<t>This document registers a YANG module in the YANG Module Names
   registry <xref target="RFC6020"/>.</t>

<figure><artwork><![CDATA[
   name: ietf-ns-topo
   namespace: urn:ietf:params:xml:ns:yang:ietf-ns-topo
   prefix: ns-topo
   reference: RFC XXXX
]]></artwork></figure>

</section>


  </middle>

  <back>

    <references title='Normative References'>





<reference anchor='RFC7950' target='https://www.rfc-editor.org/info/rfc7950'>
<front>
<title>The YANG 1.1 Data Modeling Language</title>
<author fullname='M. Bjorklund' initials='M.' role='editor' surname='Bjorklund'><organization/></author>
<date month='August' year='2016'/>
<abstract><t>YANG is a data modeling language used to model configuration data, state data, Remote Procedure Calls, and notifications for network management protocols.  This document describes the syntax and semantics of version 1.1 of the YANG language.  YANG version 1.1 is a maintenance release of the YANG language, addressing ambiguities and defects in the original specification.  There are a small number of backward incompatibilities from YANG version 1.  This document also specifies the YANG mappings to the Network Configuration Protocol (NETCONF).</t></abstract>
</front>
<seriesInfo name='RFC' value='7950'/>
<seriesInfo name='DOI' value='10.17487/RFC7950'/>
</reference>



<reference anchor='RFC8453' target='https://www.rfc-editor.org/info/rfc8453'>
<front>
<title>Framework for Abstraction and Control of TE Networks (ACTN)</title>
<author fullname='D. Ceccarelli' initials='D.' role='editor' surname='Ceccarelli'><organization/></author>
<author fullname='Y. Lee' initials='Y.' role='editor' surname='Lee'><organization/></author>
<date month='August' year='2018'/>
<abstract><t>Traffic Engineered (TE) networks have a variety of mechanisms to facilitate the separation of the data plane and control plane.  They also have a range of management and provisioning protocols to configure and activate network resources.  These mechanisms represent key technologies for enabling flexible and dynamic networking.  The term &quot;Traffic Engineered network&quot; refers to a network that uses any connection-oriented technology under the control of a distributed or centralized control plane to support dynamic provisioning of end-to- end connectivity.</t><t>Abstraction of network resources is a technique that can be applied to a single network domain or across multiple domains to create a single virtualized network that is under the control of a network operator or the customer of the operator that actually owns the network resources.</t><t>This document provides a framework for Abstraction and Control of TE Networks (ACTN) to support virtual network services and connectivity services.</t></abstract>
</front>
<seriesInfo name='RFC' value='8453'/>
<seriesInfo name='DOI' value='10.17487/RFC8453'/>
</reference>



<reference anchor='RFC8342' target='https://www.rfc-editor.org/info/rfc8342'>
<front>
<title>Network Management Datastore Architecture (NMDA)</title>
<author fullname='M. Bjorklund' initials='M.' surname='Bjorklund'><organization/></author>
<author fullname='J. Schoenwaelder' initials='J.' surname='Schoenwaelder'><organization/></author>
<author fullname='P. Shafer' initials='P.' surname='Shafer'><organization/></author>
<author fullname='K. Watsen' initials='K.' surname='Watsen'><organization/></author>
<author fullname='R. Wilton' initials='R.' surname='Wilton'><organization/></author>
<date month='March' year='2018'/>
<abstract><t>Datastores are a fundamental concept binding the data models written in the YANG data modeling language to network management protocols such as the Network Configuration Protocol (NETCONF) and RESTCONF. This document defines an architectural framework for datastores based on the experience gained with the initial simpler model, addressing requirements that were not well supported in the initial model.  This document updates RFC 7950.</t></abstract>
</front>
<seriesInfo name='RFC' value='8342'/>
<seriesInfo name='DOI' value='10.17487/RFC8342'/>
</reference>



<reference anchor='RFC2119' target='https://www.rfc-editor.org/info/rfc2119'>
<front>
<title>Key words for use in RFCs to Indicate Requirement Levels</title>
<author fullname='S. Bradner' initials='S.' surname='Bradner'><organization/></author>
<date month='March' year='1997'/>
<abstract><t>In many standards track documents several words are used to signify the requirements in the specification.  These words are often capitalized. This document defines these words as they should be interpreted in IETF documents.  This document specifies an Internet Best Current Practices for the Internet Community, and requests discussion and suggestions for improvements.</t></abstract>
</front>
<seriesInfo name='BCP' value='14'/>
<seriesInfo name='RFC' value='2119'/>
<seriesInfo name='DOI' value='10.17487/RFC2119'/>
</reference>



<reference anchor='RFC8174' target='https://www.rfc-editor.org/info/rfc8174'>
<front>
<title>Ambiguity of Uppercase vs Lowercase in RFC 2119 Key Words</title>
<author fullname='B. Leiba' initials='B.' surname='Leiba'><organization/></author>
<date month='May' year='2017'/>
<abstract><t>RFC 2119 specifies common key words that may be used in protocol  specifications.  This document aims to reduce the ambiguity by clarifying that only UPPERCASE usage of the key words have the  defined special meanings.</t></abstract>
</front>
<seriesInfo name='BCP' value='14'/>
<seriesInfo name='RFC' value='8174'/>
<seriesInfo name='DOI' value='10.17487/RFC8174'/>
</reference>



<reference anchor='RFC8340' target='https://www.rfc-editor.org/info/rfc8340'>
<front>
<title>YANG Tree Diagrams</title>
<author fullname='M. Bjorklund' initials='M.' surname='Bjorklund'><organization/></author>
<author fullname='L. Berger' initials='L.' role='editor' surname='Berger'><organization/></author>
<date month='March' year='2018'/>
<abstract><t>This document captures the current syntax used in YANG module tree diagrams.  The purpose of this document is to provide a single location for this definition.  This syntax may be updated from time to time based on the evolution of the YANG language.</t></abstract>
</front>
<seriesInfo name='BCP' value='215'/>
<seriesInfo name='RFC' value='8340'/>
<seriesInfo name='DOI' value='10.17487/RFC8340'/>
</reference>



<reference anchor='RFC6991' target='https://www.rfc-editor.org/info/rfc6991'>
<front>
<title>Common YANG Data Types</title>
<author fullname='J. Schoenwaelder' initials='J.' role='editor' surname='Schoenwaelder'><organization/></author>
<date month='July' year='2013'/>
<abstract><t>This document introduces a collection of common data types to be used with the YANG data modeling language.  This document obsoletes RFC 6021.</t></abstract>
</front>
<seriesInfo name='RFC' value='6991'/>
<seriesInfo name='DOI' value='10.17487/RFC6991'/>
</reference>



<reference anchor='RFC8345' target='https://www.rfc-editor.org/info/rfc8345'>
<front>
<title>A YANG Data Model for Network Topologies</title>
<author fullname='A. Clemm' initials='A.' surname='Clemm'><organization/></author>
<author fullname='J. Medved' initials='J.' surname='Medved'><organization/></author>
<author fullname='R. Varga' initials='R.' surname='Varga'><organization/></author>
<author fullname='N. Bahadur' initials='N.' surname='Bahadur'><organization/></author>
<author fullname='H. Ananthakrishnan' initials='H.' surname='Ananthakrishnan'><organization/></author>
<author fullname='X. Liu' initials='X.' surname='Liu'><organization/></author>
<date month='March' year='2018'/>
<abstract><t>This document defines an abstract (generic, or base) YANG data model for network/service topologies and inventories.  The data model serves as a base model that is augmented with technology-specific details in other, more specific topology and inventory data models.</t></abstract>
</front>
<seriesInfo name='RFC' value='8345'/>
<seriesInfo name='DOI' value='10.17487/RFC8345'/>
</reference>



<reference anchor='RFC8795' target='https://www.rfc-editor.org/info/rfc8795'>
<front>
<title>YANG Data Model for Traffic Engineering (TE) Topologies</title>
<author fullname='X. Liu' initials='X.' surname='Liu'><organization/></author>
<author fullname='I. Bryskin' initials='I.' surname='Bryskin'><organization/></author>
<author fullname='V. Beeram' initials='V.' surname='Beeram'><organization/></author>
<author fullname='T. Saad' initials='T.' surname='Saad'><organization/></author>
<author fullname='H. Shah' initials='H.' surname='Shah'><organization/></author>
<author fullname='O. Gonzalez de Dios' initials='O.' surname='Gonzalez de Dios'><organization/></author>
<date month='August' year='2020'/>
<abstract><t>This document defines a YANG data model for representing, retrieving, and manipulating Traffic Engineering (TE) Topologies. The model serves as a base model that other technology-specific TE topology models can augment.</t></abstract>
</front>
<seriesInfo name='RFC' value='8795'/>
<seriesInfo name='DOI' value='10.17487/RFC8795'/>
</reference>



<reference anchor='RFC8776' target='https://www.rfc-editor.org/info/rfc8776'>
<front>
<title>Common YANG Data Types for Traffic Engineering</title>
<author fullname='T. Saad' initials='T.' surname='Saad'><organization/></author>
<author fullname='R. Gandhi' initials='R.' surname='Gandhi'><organization/></author>
<author fullname='X. Liu' initials='X.' surname='Liu'><organization/></author>
<author fullname='V. Beeram' initials='V.' surname='Beeram'><organization/></author>
<author fullname='I. Bryskin' initials='I.' surname='Bryskin'><organization/></author>
<date month='June' year='2020'/>
<abstract><t>This document defines a collection of common data types and groupings in YANG data modeling language. These derived common types and groupings are intended to be imported by modules that model Traffic Engineering (TE) configuration and state capabilities.</t></abstract>
</front>
<seriesInfo name='RFC' value='8776'/>
<seriesInfo name='DOI' value='10.17487/RFC8776'/>
</reference>



<reference anchor='RFC6241' target='https://www.rfc-editor.org/info/rfc6241'>
<front>
<title>Network Configuration Protocol (NETCONF)</title>
<author fullname='R. Enns' initials='R.' role='editor' surname='Enns'><organization/></author>
<author fullname='M. Bjorklund' initials='M.' role='editor' surname='Bjorklund'><organization/></author>
<author fullname='J. Schoenwaelder' initials='J.' role='editor' surname='Schoenwaelder'><organization/></author>
<author fullname='A. Bierman' initials='A.' role='editor' surname='Bierman'><organization/></author>
<date month='June' year='2011'/>
<abstract><t>The Network Configuration Protocol (NETCONF) defined in this document provides mechanisms to install, manipulate, and delete the configuration of network devices.  It uses an Extensible Markup Language (XML)-based data encoding for the configuration data as well as the protocol messages.  The NETCONF protocol operations are realized as remote procedure calls (RPCs).  This document obsoletes RFC 4741.  [STANDARDS-TRACK]</t></abstract>
</front>
<seriesInfo name='RFC' value='6241'/>
<seriesInfo name='DOI' value='10.17487/RFC6241'/>
</reference>



<reference anchor='RFC8040' target='https://www.rfc-editor.org/info/rfc8040'>
<front>
<title>RESTCONF Protocol</title>
<author fullname='A. Bierman' initials='A.' surname='Bierman'><organization/></author>
<author fullname='M. Bjorklund' initials='M.' surname='Bjorklund'><organization/></author>
<author fullname='K. Watsen' initials='K.' surname='Watsen'><organization/></author>
<date month='January' year='2017'/>
<abstract><t>This document describes an HTTP-based protocol that provides a programmatic interface for accessing data defined in YANG, using the datastore concepts defined in the Network Configuration Protocol (NETCONF).</t></abstract>
</front>
<seriesInfo name='RFC' value='8040'/>
<seriesInfo name='DOI' value='10.17487/RFC8040'/>
</reference>



<reference anchor='RFC6242' target='https://www.rfc-editor.org/info/rfc6242'>
<front>
<title>Using the NETCONF Protocol over Secure Shell (SSH)</title>
<author fullname='M. Wasserman' initials='M.' surname='Wasserman'><organization/></author>
<date month='June' year='2011'/>
<abstract><t>This document describes a method for invoking and running the Network Configuration Protocol (NETCONF) within a Secure Shell (SSH) session as an SSH subsystem.  This document obsoletes RFC 4742.  [STANDARDS-TRACK]</t></abstract>
</front>
<seriesInfo name='RFC' value='6242'/>
<seriesInfo name='DOI' value='10.17487/RFC6242'/>
</reference>



<reference anchor='RFC8446' target='https://www.rfc-editor.org/info/rfc8446'>
<front>
<title>The Transport Layer Security (TLS) Protocol Version 1.3</title>
<author fullname='E. Rescorla' initials='E.' surname='Rescorla'><organization/></author>
<date month='August' year='2018'/>
<abstract><t>This document specifies version 1.3 of the Transport Layer Security (TLS) protocol.  TLS allows client/server applications to communicate over the Internet in a way that is designed to prevent eavesdropping, tampering, and message forgery.</t><t>This document updates RFCs 5705 and 6066, and obsoletes RFCs 5077, 5246, and 6961.  This document also specifies new requirements for TLS 1.2 implementations.</t></abstract>
</front>
<seriesInfo name='RFC' value='8446'/>
<seriesInfo name='DOI' value='10.17487/RFC8446'/>
</reference>



<reference anchor='RFC8341' target='https://www.rfc-editor.org/info/rfc8341'>
<front>
<title>Network Configuration Access Control Model</title>
<author fullname='A. Bierman' initials='A.' surname='Bierman'><organization/></author>
<author fullname='M. Bjorklund' initials='M.' surname='Bjorklund'><organization/></author>
<date month='March' year='2018'/>
<abstract><t>The standardization of network configuration interfaces for use with the Network Configuration Protocol (NETCONF) or the RESTCONF protocol requires a structured and secure operating environment that promotes human usability and multi-vendor interoperability.  There is a need for standard mechanisms to restrict NETCONF or RESTCONF protocol access for particular users to a preconfigured subset of all available NETCONF or RESTCONF protocol operations and content.  This document defines such an access control model.</t><t>This document obsoletes RFC 6536.</t></abstract>
</front>
<seriesInfo name='STD' value='91'/>
<seriesInfo name='RFC' value='8341'/>
<seriesInfo name='DOI' value='10.17487/RFC8341'/>
</reference>



<reference anchor='RFC3688' target='https://www.rfc-editor.org/info/rfc3688'>
<front>
<title>The IETF XML Registry</title>
<author fullname='M. Mealling' initials='M.' surname='Mealling'><organization/></author>
<date month='January' year='2004'/>
<abstract><t>This document describes an IANA maintained registry for IETF standards which use Extensible Markup Language (XML) related items such as Namespaces, Document Type Declarations (DTDs), Schemas, and Resource Description Framework (RDF) Schemas.</t></abstract>
</front>
<seriesInfo name='BCP' value='81'/>
<seriesInfo name='RFC' value='3688'/>
<seriesInfo name='DOI' value='10.17487/RFC3688'/>
</reference>



<reference anchor='RFC6020' target='https://www.rfc-editor.org/info/rfc6020'>
<front>
<title>YANG - A Data Modeling Language for the Network Configuration Protocol (NETCONF)</title>
<author fullname='M. Bjorklund' initials='M.' role='editor' surname='Bjorklund'><organization/></author>
<date month='October' year='2010'/>
<abstract><t>YANG is a data modeling language used to model configuration and state data manipulated by the Network Configuration Protocol (NETCONF), NETCONF remote procedure calls, and NETCONF notifications. [STANDARDS-TRACK]</t></abstract>
</front>
<seriesInfo name='RFC' value='6020'/>
<seriesInfo name='DOI' value='10.17487/RFC6020'/>
</reference>



<reference anchor='RFC7951' target='https://www.rfc-editor.org/info/rfc7951'>
<front>
<title>JSON Encoding of Data Modeled with YANG</title>
<author fullname='L. Lhotka' initials='L.' surname='Lhotka'><organization/></author>
<date month='August' year='2016'/>
<abstract><t>This document defines encoding rules for representing configuration data, state data, parameters of Remote Procedure Call (RPC) operations or actions, and notifications defined using YANG as JavaScript Object Notation (JSON) text.</t></abstract>
</front>
<seriesInfo name='RFC' value='7951'/>
<seriesInfo name='DOI' value='10.17487/RFC7951'/>
</reference>




    </references>

    <references title='Informative References'>




<reference anchor='I-D.ietf-teas-ietf-network-slices' target='https://datatracker.ietf.org/doc/html/draft-ietf-teas-ietf-network-slices-19'>
   <front>
      <title>A Framework for IETF Network Slices</title>
      <author fullname='Adrian Farrel' initials='A.' surname='Farrel'>
         <organization>Old Dog Consulting</organization>
      </author>
      <author fullname='John Drake' initials='J.' surname='Drake'>
         <organization>Juniper Networks</organization>
      </author>
      <author fullname='Reza Rokui' initials='R.' surname='Rokui'>
         <organization>Ciena</organization>
      </author>
      <author fullname='Shunsuke Homma' initials='S.' surname='Homma'>
         <organization>NTT</organization>
      </author>
      <author fullname='Kiran Makhijani' initials='K.' surname='Makhijani'>
         <organization>Futurewei</organization>
      </author>
      <author fullname='Luis M. Contreras' initials='L. M.' surname='Contreras'>
         <organization>Telefonica</organization>
      </author>
      <author fullname='Jeff Tantsura' initials='J.' surname='Tantsura'>
         <organization>Microsoft Inc.</organization>
      </author>
      <date day='21' month='January' year='2023'/>
      <abstract>
	 <t>   This document describes network slicing in the context of networks
   built from IETF technologies.  It defines the term &quot;IETF Network
   Slice&quot; and establishes the general principles of network slicing in
   the IETF context.

   The document discusses the general framework for requesting and
   operating IETF Network Slices, the characteristics of an IETF Network
   Slice, the necessary system components and interfaces, and how
   abstract requests can be mapped to more specific technologies.  The
   document also discusses related considerations with monitoring and
   security.

   This document also provides definitions of related terms to enable
   consistent usage in other IETF documents that describe or use aspects
   of IETF Network Slices.

	 </t>
      </abstract>
   </front>
   <seriesInfo name='Internet-Draft' value='draft-ietf-teas-ietf-network-slices-19'/>
   
</reference>


<reference anchor='I-D.ietf-ccamp-yang-otn-slicing' target='https://datatracker.ietf.org/doc/html/draft-ietf-ccamp-yang-otn-slicing-03'>
   <front>
      <title>Framework and Data Model for OTN Network Slicing</title>
      <author fullname='Aihua Guo' initials='A.' surname='Guo'>
         <organization>Futurewei Technologies</organization>
      </author>
      <author fullname='Luis M. Contreras' initials='L. M.' surname='Contreras'>
         <organization>Telefonica</organization>
      </author>
      <author fullname='Sergio Belotti' initials='S.' surname='Belotti'>
         <organization>Nokia</organization>
      </author>
      <author fullname='Reza Rokui' initials='R.' surname='Rokui'>
         <organization>Ciena</organization>
      </author>
      <author fullname='Yunbin Xu' initials='Y.' surname='Xu'>
         <organization>CAICT</organization>
      </author>
      <author fullname='Yang Zhao' initials='Y.' surname='Zhao'>
         <organization>China Mobile</organization>
      </author>
      <author fullname='Xufeng Liu' initials='X.' surname='Liu'>
         <organization>IBM Corporation</organization>
      </author>
      <date day='24' month='October' year='2022'/>
      <abstract>
	 <t>   The requirement of slicing network resources with desired quality of
   service is emerging at every network technology, including the
   Optical Transport Networks (OTN).  As a part of the transport
   network, OTN can provide hard pipes with guaranteed data isolation
   and deterministic low latency, which are highly demanded in the
   Service Level Agreement (SLA).

   This document describes a framework for OTN network slicing and a
   YANG data model augmentation of the OTN topology model.  Additional
   YANG data model augmentations will be defined in a future version of
   this draft.

	 </t>
      </abstract>
   </front>
   <seriesInfo name='Internet-Draft' value='draft-ietf-ccamp-yang-otn-slicing-03'/>
   
</reference>


<reference anchor='I-D.contreras-teas-slice-controller-models' target='https://datatracker.ietf.org/doc/html/draft-contreras-teas-slice-controller-models-04'>
   <front>
      <title>IETF Network Slice Controller and its associated data models</title>
      <author fullname='Luis M. Contreras' initials='L. M.' surname='Contreras'>
         <organization>Telefonica</organization>
      </author>
      <author fullname='Reza Rokui' initials='R.' surname='Rokui'>
         <organization>Ciena</organization>
      </author>
      <author fullname='Jeff Tantsura' initials='J.' surname='Tantsura'>
         <organization>Microsoft</organization>
      </author>
      <author fullname='Bo Wu' initials='B.' surname='Wu'>
         <organization>Huawei</organization>
      </author>
      <author fullname='Xufeng Liu' initials='X.' surname='Liu'>
         <organization>IBM Corporation</organization>
      </author>
      <author fullname='Dhruv Dhody' initials='D.' surname='Dhody'>
         <organization>Huawei</organization>
      </author>
      <author fullname='Sergio Belotti' initials='S.' surname='Belotti'>
         <organization>Nokia</organization>
      </author>
      <date day='24' month='October' year='2022'/>
      <abstract>
	 <t>   This document describes the major functional components of an IETF
   Network Slice Controller (NSC) as well as references the data models
   required for supporting the requests of IETF network slice services
   and their realization.

	 </t>
      </abstract>
   </front>
   <seriesInfo name='Internet-Draft' value='draft-contreras-teas-slice-controller-models-04'/>
   
</reference>


<reference anchor='I-D.ietf-teas-ietf-network-slice-nbi-yang' target='https://datatracker.ietf.org/doc/html/draft-ietf-teas-ietf-network-slice-nbi-yang-03'>
   <front>
      <title>IETF Network Slice Service YANG Model</title>
      <author fullname='Bo Wu' initials='B.' surname='Wu'>
         <organization>Huawei Technologies</organization>
      </author>
      <author fullname='Dhruv Dhody' initials='D.' surname='Dhody'>
         <organization>Huawei Technologies</organization>
      </author>
      <author fullname='Reza Rokui' initials='R.' surname='Rokui'>
         <organization>Ciena</organization>
      </author>
      <author fullname='Tarek Saad' initials='T.' surname='Saad'>
         <organization>Cisco Systems, Inc</organization>
      </author>
      <author fullname='Liuyan Han' initials='L.' surname='Han'>
         <organization>China Mobile</organization>
      </author>
      <author fullname='John Mullooly' initials='J.' surname='Mullooly'>
         <organization>Cisco Systems, Inc</organization>
      </author>
      <date day='24' month='October' year='2022'/>
      <abstract>
	 <t>   This document defines a YANG model for the IETF Network Slice
   service.  The model can be used by an IETF Network Slice customer to
   manage IETF Network Slices.

	 </t>
      </abstract>
   </front>
   <seriesInfo name='Internet-Draft' value='draft-ietf-teas-ietf-network-slice-nbi-yang-03'/>
   
</reference>


<reference anchor='I-D.ietf-teas-actn-yang' target='https://datatracker.ietf.org/doc/html/draft-ietf-teas-actn-yang-10'>
   <front>
      <title>Applicability of YANG models for Abstraction and Control of Traffic Engineered Networks</title>
      <author fullname='Young Lee' initials='Y.' surname='Lee'>
         <organization>Samsung</organization>
      </author>
      <author fullname='Haomian Zheng' initials='H.' surname='Zheng'>
         <organization>Huawei</organization>
      </author>
      <author fullname='Daniele Ceccarelli' initials='D.' surname='Ceccarelli'>
         <organization>Ericsson</organization>
      </author>
      <author fullname='Bin Yeong Yoon' initials='B. Y.' surname='Yoon'>
         <organization>ETRI</organization>
      </author>
      <author fullname='Sergio Belotti' initials='S.' surname='Belotti'>
         <organization>Nokia</organization>
      </author>
      <date day='4' month='September' year='2022'/>
      <abstract>
	 <t>   Abstraction and Control of TE Networks (ACTN) refers to the set of
   virtual network operations needed to orchestrate, control and manage
   large-scale multi-domain TE networks, so as to facilitate network
   programmability, automation, efficient resource sharing, and end-to-
   end virtual service aware connectivity and network function
   virtualization services.

   This document explains how the different types of YANG models
   defined in the Operations and Management Area and in the Routing
   Area are applicable to the ACTN framework. This document also shows
   how the ACTN architecture can be satisfied using classes of data
   model that have already been defined, and discusses the
   applicability of specific data models that are under development. It
   also highlights where new data models may need to be developed.

	 </t>
      </abstract>
   </front>
   <seriesInfo name='Internet-Draft' value='draft-ietf-teas-actn-yang-10'/>
   
</reference>




    </references>


<section anchor="acknowledgments"><name>Acknowledgments</name>

<t>The TEAS Network Slicing Design Team (NSDT) members included Aijun
   Wang, Dong Jie, Eric Gray, Jari Arkko, Jeff Tantsura, John E Drake,
   Luis M.  Contreras, Rakesh Gandhi, Ran Chen, Reza Rokui, Ricard
   Vilalta, Ron Bonica, Sergio Belotti, Tomonobu Niwa, Xuesong Geng, and
   Xufeng Liu.</t>

</section>
<section anchor="data-tree-for-the-example-in-section-31"><name>Data Tree for the Example in Section 3.1</name>

<section anchor="native-topology"><name>Native Topology</name>
<t>This section contains an example of an instance data tree in the JSON
   encoding <xref target="RFC7951"/>.  The example instantiates "ietf-network" for the
   native topology depicted in <xref target="fig-ns-topo-example"/>.</t>

<figure><artwork><![CDATA[
   {
     "ietf-network:networks": {
       "network": [
         {
           "network-id":"example-native-topology",
           "network-types": {
           },
           "node": [
             {
               "node-id":"R1",
               "ietf-network-topology:termination-point": [
                 {
                   "tp-id":"1-0-1"
                 },
                 {
                   "tp-id":"1-0-2"
                 },
                 {
                   "tp-id":"1-2-1"
                 },
                 {
                   "tp-id":"1-2-2"
                 }
               ]
             },
             {
               "node-id":"R2",
               "ietf-network-topology:termination-point": [
                 {
                   "tp-id":"2-1-1"
                 },
                 {
                   "tp-id":"2-1-2"
                 },
                 {
                   "tp-id":"2-3-1"
                 },
                 {
                   "tp-id":"2-4-1"
                 }
               ]
             },
             {
               "node-id":"R3",
               "ietf-network-topology:termination-point": [
                 {
                   "tp-id":"3-0-1"
                 },
                 {
                   "tp-id":"3-2-1"
                 }
               ]
             },
             {
               "node-id":"R4",
               "ietf-network-topology:termination-point": [
                 {
                   "tp-id":"4-0-1"
                 },
                 {
                   "tp-id":"4-2-1"
                 }
               ]
             }
           ],
           "ietf-network-topology:link": [
             {
               "link-id":"R1,1-0-1,,",
               "source": {
                 "source-node":"R1",
                 "source-tp":"1-0-1"
               }
             },
             {
               "link-id":",,R1,1-0-1",
               "destination": {
                 "dest-node":"R1",
                 "dest-tp":"1-0-1"
               }
             },
             {
               "link-id":"R1,1-0-2,,",
               "source": {
                 "source-node":"R1",
                 "source-tp":"1-0-2"
               }
             },
             {
               "link-id":",,R1,1-0-2",
               "destination": {
                 "dest-node":"R1",
                 "dest-tp":"1-0-2"
               }
             },
             {
               "link-id":"R1,1-2-1,R2,2-1-1",
               "source": {
                 "source-node":"R1",
                 "source-tp":"1-2-1"
               },
               "destination": {
                 "dest-node":"R2",
                 "dest-tp":"2-1-1"
               }
             },
             {
               "link-id":"R2,2-1-1,R1,1-2-1",
               "source": {
                 "source-node":"R2",
                 "source-tp":"2-1-1"
               },
               "destination": {
                 "dest-node":"R1",
                 "dest-tp":"1-2-1"
               }
             },
             {
               "link-id":"R1,1-2-2,R2,2-1-2",
               "source": {
                 "source-node":"R1",
                 "source-tp":"1-2-2"
               },
               "destination": {
                 "dest-node":"R2",
                 "dest-tp":"2-1-2"
               }
             },
             {
               "link-id":"R2,2-1-2,R1,1-2-2",
               "source": {
                 "source-node":"R2",
                 "source-tp":"2-1-2"
               },
               "destination": {
                 "dest-node":"R1",
                 "dest-tp":"1-2-2"
               }
             },
             {
               "link-id":"R2,2-3-1,R3,3-2-1",
               "source": {
                 "source-node":"R2",
                 "source-tp":"2-3-1"
               },
               "destination": {
                 "dest-node":"R3",
                 "dest-tp":"3-2-1"
               }
             },
             {
               "link-id":"R3,3-2-1,R2,2-3-1",
               "source": {
                 "source-node":"R3",
                 "source-tp":"3-2-1"
               },
               "destination": {
                 "dest-node":"R2",
                 "dest-tp":"2-3-1"
               }
             },
             {
               "link-id":"R2,2-4-1,R4,4-2-1",
               "source": {
                 "source-node":"R2",
                 "source-tp":"2-4-1"
               },
               "destination": {
                 "dest-node":"R4",
                 "dest-tp":"4-2-1"
               }
             },
             {
               "link-id":"R4,4-2-1,R2,2-4-1",
               "source": {
                 "source-node":"R4",
                 "source-tp":"4-2-1"
               },
               "destination": {
                 "dest-node":"R2",
                 "dest-tp":"2-4-1"
               }
             },
             {
               "link-id":"R3,3-0-1,,",
               "source": {
                 "source-node":"R3",
                 "source-tp":"3-0-1"
               }
             },
             {
               "link-id":",,R3,3-0-1",
               "destination": {
                 "dest-node":"R3",
                 "dest-tp":"3-0-1"
               }
             },
             {
               "link-id":"R4,4-0-1,,",
               "source": {
                 "source-node":"R4",
                 "source-tp":"4-0-1"
               }
             },
             {
               "link-id":",,R4,4-0-1",
               "destination": {
                 "dest-node":"R4",
                 "dest-tp":"4-0-1"
               }
             }
           ]
         }
       ]
     }
   }
]]></artwork></figure>

</section>
</section>


  </back>

<!-- ##markdown-source:
H4sIAFDA7mMAA+09a3PbtrLf9Stw1ZlbuxXl+NE0VU/bOLaTuhM/jqU2PXNe
Q0mQxZoidQnSjhv7/va7DwAESciSYzen7Q1nmloksNhd7C4WiwUQBEFrlI6j
5LwninwSPGu18iiPZU8cHgxeimOZX6XZhejH0UiKQTpP4/T8Wvxt9/iV2A/z
UBylYxm3WuFwmMnL3qLyTtFxOkrCGcAfZ+EkD+KoCHIZqiDPwkTN0ywPEoYR
KIQRXIfJefDkaQtfnWdpMe+JwcFuX7yB34C1eIXvWqMwl+dpdt0TKh+3onnW
E3lWqHzryZOvnmy1WioPk/G/wzhNoOVrqVrzqCf+nqejjlDQZiYnCv66nvEf
o3Q2k0mu/gmEFfk0zXotIQL4TwjG/ediIqHt11FBL9MMuHf44kjspRmQEOZR
mtAHOQujuCfeUvEu0NqNZD55fo6vu9BKDewPcjIRgxBaLrKwhHwUjbJUpZPc
hfkLlAWi8rshHgJTxIvsWgGvHFSTcXQZjYswdiFG/x5ywefX4TRNPdBeF5ES
R10gMwGWZaEqQQ5kLCdpEo1CF2QMFWbReSERN11nVmRRHKfPc1vD09Jfo0S8
cZj7fRFeycgFPQQg3avi+ZS+eED0ZXYepeKFjNM8j0pQx+lFVEGSC3aHXPB5
gt898M7kr6E4Sy8KB9ZeJJMKrCzDAs9H+N4DYzcCdMWrIi1BvCzyIpM14kIs
d16kSzo3B4EWLwoV3cWoCEt1h1DK5VUrCAIRDhWo3ShvYfndhFVeq58g9ROz
8FoUSoowsaVFbtQ6T8VYqlEWDaWIklwmYzkWCKuAv7IYqk5A/KDnEznKQeLy
SCoxBPhSJho+1JmnUFd1xW4NPhRGWFMZz0U+lWIE+pzOZIbNAswJyFUmq+gq
cRXlU6GmYQaYZFKlRTZiMOEsTc5VbrFJE1B0MAruCzECMoGWELEFizImcCCK
2Dw1QJAUNCqB1C7xbTAFpQCrVqDJsPxQImQrOUbTN0PTR8yYhUl4jnYLmsba
pBZpHNOrJgOoTrNboEE5iRJAkNX63bvvDoN9kha2pvRXxZCq29su9/osGo9j
2Wp9AnYA2h4XRLyXFmzDUvLu3X+dvdz78qsvntze1snK5By4DZWAjg5CMnRa
HlsqfdQAS60sonjrryUfOuJqKqG3sSPqdeG15gbWhd5amRtEsa3t0gRsAFFA
mc4mIYipEVojg8r03zxLwZLiCy3qJJYhixOSDiNPLoE/eRbJyzDGYSZFekGI
VTHHAc+lGJEjUUCuK5ldAq5dxBJGufMpkA+IEYbA11IhQGwRSCzDrJRVBDMK
5yEYSlY8xAY/hpdgF8JhLEsFEekEP7kEQau7lRag9P8UEjQI6ExgsM0jJIz0
Lazj7wIidc0kFiaW4lCsiZLVBqIEyqHkhXF8TWZkPsZqUa6o8Yi/ArZY1gxh
pTmCAYW/1zXWNNoRsnveBdaN0eERJLczwBIZLhJgK74CIb3ocNP4ARQa2qW+
HgIHr6IxEAzsCnVB5KruXRbPdC65/wE16nzDXbCiBsMugnuDrMMaZOGgTAo/
wELI0TRMYNzkHiuF0lV60iJSNASQE9w8u4YvIIYzat4Ys3kxjCM1hWrQEa4d
JSSMDpCGs+wbtc8BkYQ4G4TnSaryaIQCDmoKFkORkwStAFBP54e5fQvDAKoH
0DeOJhNQYrAsFjSpNnaKODzdODp93V8LBqfrHXEyOCbq3+wfdTWK4JqlGXRh
qQM0OAGFMD6NWWM0TsMQeM1F4NfVNBpNmbk+VWPegloWUAqguNZjNApnc3ZB
0zwJdJXb2w42TXQW5yxypAcOx9RcjqJJhWNscHaVHSOoI/s89oht4JBjyq27
xBaMfWFjRmUWMNaICXapY7mqpjCvGHRgz9zoiL/a6uNJkAwj4gxYUgEjCSkV
UcJi5pqAT5W4jOTVIlybiGp512AG13Mptow5dGvxkPRs54tt157Xx10PH0hN
lNEIPWvB+kc4bhGLaNICmgLDy242mkbQueipibXjo/3dddP09s4WNf3JJ+AC
Z7OIu9+iciGvBYAeK9E++rE/aHf4/+L4hP4+O/jrj4dnB/v4d//73dev7R9c
AsHA75MfX+si+FdZee/k6OjgeJ/rw1tRe3W0+7d2x4xU7ZPTweHJ8e7rdpMh
OIYCL7Qbl8FYnrNKuaKKQF7snYrNHU381ubmV+AKaE5sfrkDP2CYTtgopkl8
rX8Cj69FOJ/D+IRtg3kn1yeco2+KbpgCly29SgRqedmPeclQGl01Mqi0tS5W
OGBPUnA7rQCXvorunUxKsR+F51k44xbwxZhfKLYhDb5MQNnSK/Y60pzNal1T
tBhQQ2hQoa1TsFXRW0kDEU19j3FsOQanXVHTh7V2OuTQs43E4jgUsfXnIcGR
5XT4C8ghe7TQaXNuaQz4I1to1MOpbpiN9TdgrkpHkfVmjVKN0gyG/3majC0/
oxm6I1AOmipi6XYM6VoeDgPdoPWfbjSx9CdBOaLKovHcwAyKzP+o/HhDIAL7
OH/6Ht9nBiHQEulmyFaRzc7BcKg6FtxjT7/6ahPE1cECaJS5CwJ/3xNEktsy
FYtpXZQaCJCbL+ogrh4MItd0GBC5bNSuggA9aYDQlDsgmpxwQXz5tE6IolZL
QszvBgio/zM87rvWu574xJU3QVGpb9pWtVA79poyzNKn2retFoAVBzAmgeU4
TnPZa52Cg6zQ653H6NNTm0YlEAmRFLMhqBtoTHSeGIfJ0dNuCQLcRskfwTCg
zfqE41uIyB4M+Tjs8Szgjsm1cWTY1tZmPdeLLM0XOOqz383eB7dDDnsir0o4
OGy2K4M2mH4yHYsGXoDxBiy249CXyKANMo60mbmG8MKdk3ErFQw64L6X00Pl
zgG0xxN6eWMaZut9JmOmchrNadimF0CBDTES95UZO8A0onlU4JRn4IdnunRj
2Min4KlOw0uc4cm6bUesgCN9cJZLFx7A9qgVE+qsYtBrsQTvN5wU6rhupWpf
u6CLa97LDSPY6DlruEsgLnJuGc67dzCTZTczyBzug5bjkMDdnlW6hUIsmk3M
Xz3LG6ZvdV+P0xz7IaYJxlii7jCkux1CHFlb/wsPU/R5af4/b9gT92NLWxjD
cPizaX7Kj6Y4R6+Fv7jt7xL6i0OWrG8bON1w31qzWH1jylRtoUBRMcWJms9d
sE5x/d4htV7CQ8KNW9LOX/BHZsZnVft6X9iE0b8WIN2l51/0r2EJCq1bzunD
ck1B9Nz+Qb2BP10C8OmVnddrMPzbhvfQK7vTFl9MHkC3sHoriOKnzsPii8Oa
X6/MAMcNVOwdDGbsV+7uAZ/QE64ZEFLYfoQmlYpUjbY2dWgPcWKMnnkljmZK
U9iurobVUYfCR+6gU9dY1nFnViFhyo/R1Ho9PfNqomuxAPcTxowipigMgJ+F
F8bFZT6A3y6JAHcWaGMmJZymGQ1HYO/YaHKILCYDbyICmjGq4i/rANTYsm00
DTFeKbMIIyOqdAHE7nwOkDjwdl0bkWZhcl0JfyAnQpheYvioFprQ1rNCzeI5
sw730ESmEiE3Ub6Aer8eAqnGVisRwbDprtiB3IkwSBTJGVVwFgnq0tXRcRhE
M0cfY4jMgDkhAUIm2CoGCTEPs5xjCmvHZ6frwCeYtZCvp8VHjWQSZlGq3jMC
LDgAdshkyLchxkfcKQ/qqnZcA/0Z9YBihZdRlhdhHP3K88JIGd4jSCUBeY55
jnHCm444DGzYC9Dn02sFYoJdinENGiyvUgOWZC4tcoyd/XS2SXB+OtsiIeJw
KigyeDclGC4tzjZ5/p0vgrWtYe2sAGuLlHDOKhxfA4oH4WjqhIt1CwZ8h8Jw
Zb9xwTpcMCThBS0s4IQTyyEoXbbkkYnIYSF2+Gfgd1OU0we1y525L+eSJwTa
zlVCxyYIHplIWKiXgihGgQFFWjwiSCOZoYfrwyhL4adKgWCx2z/c00tJCgwG
FJiEwywa2XAfCLwWnQ6aBkTurXjRddyoH/onxwIG3nRsViGMi6y030T2OiQ7
aq2lIYXjudGvJHvzMlxSWYun4E1c4Eyl9KOE2DPx94FvgrigjKlcXexH6M3K
1TJnrKELn88rw6jz6/Oai1N5OA4Aco3xAf59A5qiowX0YUHVjRVabdZqrVqw
+fyjSg2ht1liuuXxOXyPLr5DNR+AjlO8dWfH0GMEQbUMCg99lrd5qkPIJXp7
pbhboV0zYnaGqgqCdhqSXVHrrTogK5E0uP+kzdc+m+CylaZs99AMd9B+4j9f
VLlXwXk5VfopGXEDEG9W5Qk/G+Wfi7XDI9q1crb9zRsXm+0lgvjQ1rYqre34
FXQ5vIXPP2pQ3q9Pntb7pGHOUCq2UCB28J+n9VaXN1uTQPEhdcuMn03p56Gm
bvAXKFEDzqq8rnNr1dJOH2mr/+H15ht6yHp/Y57lBvz3KOZ6GLkHC52HW63M
bWv+spnY1oNeg2qSy08Vb7p9K3A+ZUK6MO85ucTlP3llFod4aYaSHMo1aXK2
8zyLhkVeTQ1xM3nKtW6O5AVij9eNy6pmtgJz6rgAXx+TMXL0UEf1kiKOLqSZ
II0xA2YSgYfLrMRlnY5et5ojXewn2tWeMp3kappSnpXNW+hq1A5MgpRByU7B
kPCRnJP14CKMoElnghlyOnPSRBglnmyYCdTguN/F4LRJw6KQNM3KKEHFLGJb
Txs6ynr8bnaVsO67zehAQs0CsHaP0XtG6DSjRy9aBjaTZExFLhKcekHTGugw
1eF5L1j4I0ozOxmkPqik4HRJVGxGhYGK8mYpNhjoORxMJTB4r6eX6VyHfnGm
jQmrpluOF0xvy97RAsO5aDSNAgF2s9IwYQ/Q+tUkLxjGaiStL29yj2AWaZjs
Zs05OTRpEY9JiojTvvgOwdU6Af+D6Q0uPjgZetcweUOWZyHom11TLKk009kr
IoxmWRODcUmZQRkzd2YYwkE7YDk+D6NMda3qOW3PQlCrt01e0ozNJBgaPrmJ
e6bBCnM0WlrzQy3sVWq5RaiD2TPMQEwArK2Z0hQOgzpRzvwxMo+TZgqKDdPL
ZkStKzSRfU5dCGJ5addwYYBVYq3/+kStN9orM2X0em9HWyLTIUBKxyCBwYiO
zkbiJXMWZmIC91gF+U6VI7xora0sLYr3yZoWmdRzRV4O7lWW8ZAwHdETG8lV
z8TMnL+dP3nxkEOmMGJkV9UFo/9aDsytu6biFCrKALgcja7XvzPjFnzurZn1
b+v635h6plouYVwCZn9nR7FYhpNMTipwWK3WnTFRQ9F9WUWiOnRySf4SOObf
tAjjlU6UqtfBNK5oFAwxl6HmSN34ynwm/q5/Iov/2ahRB0yLgvbhASu/dmhf
WLNIorws4KPArXQZwpSpTvqySkTRd6L6FCDFT3d8vFJyVGSA/Wei/iykiytG
KuXwer2tZRVn4dsgHY2KeZhAx5I2f1di+cxbJS8arZRVNp96CculRE4F7NqE
UXUNRjiygAq9QjEjtJMiGdndCc1i40j9glYjkUp91yhjXFuTDNCDP6h9t9oS
BDBBcbkWpCAyM+0KBiBBGGXn3lrSQWDDwmswULHMMHzmcH6Ywssw8eopQh+j
fayL0mLZg4EJRu7AiS2atpZg6GNEjR2r2FWw1h9N4keTWOfVR5P4SCbxox1a
2Q5tJHnP8TsD8jtd42QmKMEkxJl/oMbzIBr7Tc1Hc/bRnJXFP5qzj+ZMf/8A
5izv4SR6uVt147VDN/e2QzceO3Tjocljh2yU+R52qFanaYdsgZXtkFujDvhu
O3RXzYV2yFtpmR3yVlpmh2q8Wt0O1SqubofqvbOCHapXWcUO1QlbZIeasuC1
Q81iXjvULNacabplVp9pLkZgwUyzxoDVTWKt4momsa6nq5jEWp3VTWJDaJea
xOVc8Le0jAVNRiyjv8GFZcTfhdhiyiv0V1at3OBmkGMYVK9bufuEaOXAn6dO
SZrCWbPCbQhlss1f9k72D8SLg1eHx/1vxSSKpWi7TT7ferK1HTzZDLY3u5iZ
2MZKHHitbp94x6MfpW1TiD5NxGZ382t+TStL85DzffBpF1nSQwA9zEebqd7b
WdxLVA/r91zAbQ1B7xpql6/5PW8OquxJMbg4la4MGFwNMLt92iapuSd260eH
VDKVyiVBA+Z2YePllpYmFvmjY9FEw+6IaTRvvniQKD0XxubLL5/2xCALJ7jI
dpCcRwmbY7MgSWgOXGA+VKobAsw2yQZeureX4MXHsqy05SB48qRX1vQdGKPX
PZx1XKdj+Q+9CBa6PmubQO3t7R6dVs95MbVp7wmfFUDl37wSb+SwJ/4yzfN5
b2MjB8ujKP2zC/A3rs43aLPDxrcWXajxOlI5VMFTMvK0RwWemyrflrkQvIWo
ceaL+xgYC8958YCrHd7hA+c9ucMDqnqqiA/SgvNEPLA8p6b4AKoFZ6Z4IPoP
jfEBXf20mG+tWXL8PisNA71DHG1neYYFbQr3HclhVozdieu5TEARR/WzJqKE
hkpcCbfnFdl0cX26gIVxoksObEmjHGsng+P1bsmqgd0AMyni+HrR/mTv5mQL
xLNJ2WliL51fZ9H5NBdro3WBgw3r6wBPSbKppDA+K1xOtYkMuDRtYfBZSMqu
9APGuOksjgVBVnaN22n3TILLxrkSOFJhQ7hADYzUOd74ZhglYUZJqzOlt7al
mQWBv9OCNoVjMkLIeRSYP4BBJ9pPNC8yVYS4UJyaVANaN7UwNCOxFxPFO4uV
2cFGyfS8t+FMXkaYw/2ivw+KTmUtCFzPBwzzqbtrf6c7Muwo2fmpEq/lOfQ8
pUsp2gRY8iPmcyUAI6qxr/P3yyJraMQUWjEEJmVpxzT65NdU5Qe4YZwBk65g
slzIg1CUk43fcNzBnY9fA0HSZHEzavAlypWMJ6QWKIowXUU6kjSnBHWrdZlk
ugR7LVvBk2fleOOoJFhymMtFlC3CNZYPiojcvU4fqw+NG59piJ+JQ3YPI5uk
8tmGHj6131hO0PTavI8KB8EXaERsZWQTpSZUgXTvJvJV/2g3OO4HAx0c6IlX
2trU6NXfO47B/El38nb3SbfuIxmskjSwCJX0kPmrIfr13cQeV40fZlOBJNit
DeOFGJh0od8OD9MCGEuLjlijg0Rs7oTDtiwcXXScrIppmI2vQjxNpHxHWzTI
tMh81F1fSBy6hr8pbboBl7TFnOaNCAuRafbEEnxOGaAeETIZjlVJ0fIO5w0a
vxt0jN/6H8ZHZywFdifWInwasrUEnd3aZHSKiWQjwtBN3wMH5Jzy2Oo5e/jQ
FuhxSqqN+UxxONdDMJ09UfWAnHqsbT8dlfQv1hnTDyYotFhg78uB45dl8v9L
DX0dx7sxOB4jMgt67K8Q4tpUcE2aSY28fZxy9xZSZcMMj0VLf499U2ybKwH6
lMXJfQEFwD9y8HVNXIk5yObxywUU1EjQ8ZV0XkV/1cEP4+WiesSfhkmZgQRA
NaZ89daTNJE11lXwWsa2NOfyuI9zaWMo2gE4yg9o8Mw0pjeI6vk7AG1O02ut
TzGmpNQDGv9eQ1hMseP/0KQZusJxf/ivc/3BnNJRW2NYJgmnXMpCQVloTnPI
jXG8Rl79WBBsLJvEhxYPnOBe9atmm40O24RKa2Dow9dunVv3h5cqouzEQU6U
yIW4pdc5EcRmeJau3m2FyFps1MWfaNOxUQfFBTi1P4VpgPxURBPBh41A2ylh
RpPLaXoFdgbzqXO9qTKvhgHwTBKbpTpLiyQ3xww5uHsd1Qe6qn5ntcanIIbZ
oRsWbjCKQ8IOprg6pHBFJk3GagX+7QpqA4gum4loL+dcH3c0vHYHiAoJnIr/
O2CUJxLeYNVCfbnDyFQUYxEL8bzgEZ1kaG0740ET10UYu1H4Bq4cgl+h+/bN
AbNULbVgAZciSZxtvtxV4jDXxwJWOFwoCfPZyvGIoMr2aFm7dUAfr+fsQOBH
26xyd7LZ012Z0t5W/AR8Fllbz7Lb+9hc9vCu8acBKVyQEyeMIla30O4qW6Pn
7lyTW6FDjTBxQIYT4mtNEmlm17J9rIezUEf+H0tcY+jf5WwHs6GcjpQrvQBd
unpWlD1LxRQwGRPtVTP828uEeN+cLepENfuVdTRCxelhE6TLamdMOd3Lu0Rw
iac0VH7g7VXkM1clRBsI9aJcxbSq/U0W233792Wzw1U8T1G0uw3Gb2jL0qsw
qe1yqRKW09LBhzQ2Dgu4073xwrHEVbZflQcgO4BAMZRZ0lQ9f45LzYtezqDa
xse25UcV7h0FOQnnLkheTJt988fvHP+c4I/UJ3fsg3UqewZhX3f+mXrUQ3Ij
em4tFp1y836DAtT8I2gGUfgfMVkll1ZXE7FUTxaWWN14/cF7aSXbVZPxT1Vz
3+RD5L7Zo54E+T8X7/GpuOL+nP96GAcfcj11Wqzvu+Adt+0Nq4DefBfVXn74
gQOjUveeVcdzVflV+QFUVtlS43L5LAxC6RZ5qfhSOjlMdExajbWiv39a64nb
lvvrXtbL1vqNhP73Z+3+HEr3XsaPwvfvYeg4Uf6PMMAThY86wN+X3atz8/en
Gn/k3vwzdc4dNVafw/xu+rNGiwHqOQPcBt5g3DMn8RiKHSi1iCeJiSoPuaie
f1om7jkQKs2+1+TJ/MN53gfH+/1v78gvp9sKdH65c/POXdnlgmw9HtRBSYD6
dFnfWfODVMhEFfpEV7N1pXIPl6mNiyL2EE3NJgRhV6w7jIdmXZSM6XBNkgFz
zREfzFlmJoZZ9bxc53xbp1SZNIGF+VBRnS+pTHBNZ8FoSO6SPh4EW+CZSFiZ
0gAVpdmZ65jMUjgy1EVa50ZgoZP/PupS4hyCKE8IorU9cV6EICU5J8hVYrjl
Wj+fdm7D1LlMQnvAKJB8mUYlJmS0oCQe2IPJnk6Ohqnv8MZmSYAM45k/qG1D
6aQ7hhM8nFUVBAWjzKaTEdBoKkcXfBxx3/S9T0qcg7AwRVAni/hOFi5zaBUA
n4V8GYs+lZjSRyjforw0YWgopNN6yoN9HRrnWZqnozTmM1URUKjE8cFg7+T4
pblfY2sH79eAts4O+u6HZ0/othWmIU6v8FIyU5Vum2IRLsVfOtm6VKBjM15n
uIUvx5ylPA3sobC6GtFnawLEPkPrTyX0y1q///16ietWHSWLtYvT94PBaX/F
5qttD173EYY57HrnqXvlkSFfC5bWc21W7BneyE59dpY+dV+GiVkxBlnF3XdW
SbCT6SDfURGHmW3B7Q4wjxkfYE16mEl76DRl4OoTsPDcqvLOOR8cIwwIxdoV
ZS0WXQCgKdXHaIfmro7qlTn1w7FdASdB1cbpCrQCsdmg04/pL7yGg/4Sa1FX
djvaz8BrZKU9Dc5eSQUNhUWcr3OPK+kioW8lG2mdQ16APY5oKofnpxVxAiRC
SyQSmAg9K7OTZHIZZWnCt8QJ8QYzEFyerPENdmAJ84AxpH2jnONUxcPkTQN3
53RWWprrrGU8g5suvUDVPKdJJgLhs9pxdctgUzbcFTUj4mZBP7N3lznXyVA3
xXjZoT4OPTanzkVou4a4x8pe1VfJ1vdeXsYS4NzFITD7jqA6NPs6vtEfCGhB
lyzrj8OchaCgYYM34XDeudU5RMvokO4ttIHnMu/gP7rXOjrDHVOrTVL7uq8b
fw+M/0Qc7h7v+kYR5gdKWKrPnaeSaBLoEh26kObHs0PFaWzYIm/u+fnoNdY/
k+e4PQAnIETC9tNnz5AEpc93VL1yCx2A6YlVt7M5wLF/9njDUI+M5eFB/xV+
Bxx64nhj92t7TDiYQKACGtIXgEKJcktdlzFhQ+SOjxm1Q5eCVrPuneMm9a1Y
fAcYWVsm3IwfT7b4pjJDLN/wW6fI4nI/RvAOsJ5wXtmYUs/uCNDkBUEghuHo
Art9d4QHMsZyrO8BMcMN3cBdP9BznzwAMZDhTKwd9/cH63he+xD5op33sdiN
filoAvAmxLth99GF+iECA3uAuTKvsvC6I34Is0jsZhcXaad6Izb8TKeJOBD7
WXjBKTRmc1G5u6gjzjANaipewfAxjfBnIvboGrryBmf4GxQjI3n/CQamOAfg
Z6BQL2iLUae2DaoDPjV4e+mwEMfRFXz+GSQFUX8l9Q23JE52gxipDG1QoM2j
ZpvAgT4Q1b31sbtJ9xt5DtwlGVPGYpvLlsrD5PWFC/YyJTIZtHFVyx2eKk9m
PeEL3stL8TatqyItSgiFDuJUZqegWcfT6LP8VY+gB88aPAZzU4j3sgQ+X9CI
tZ5ZVlqwE+92r5x5mnur4N3fy4laJTxsr7aKxu1eWzcYMIp2d2i7463C2Qq9
KsDbWlmMa1aab6BgyzEOZ5vV5hqkWrQ8odFGS97WCGQ+5/Y2gyfBZtsTbG5g
sQqkrUeCtPVoOG35caq/qp2JU2/pzh7b+rA9Brx5JO4gpMfpsa1g+9Fw2vFD
eswe2/6wPbb9aDq2vUgzHpM7Ox+WOzuPxp2d9+WO+/OfVQvuJ5wCuivYdSxn
7HqHTG2n4+EuR3jqY0nlY8BDiXd8KAvl84Um/fa+ElHi3ukY7D24w/wi1zKw
gAAssQR9KvLbIK9R3/pAjG/a08dgvG+I+Q0Y/6jIE+qgkJ2zrQ6PWb89/336
37Qj92Wdh/sV1vlH5IewTnOsY3j4QNb5CXBZt4CEDyB13i57sNRtGanzac7j
S51HcT6I1D2uwmqOGal7KOtWk7rfgnWrSN3js24bFXa7s/2BFNbncT+cdR7X
uMI6vwf6ENZpjnUMDx/IOj8BLusWkPABFNbbZQ+Uuh1k3U5n5wNJnW929nDW
eaYcFdb5PfuHsE5zrGN4+EDW+QlwWbeAhA8gdd4ue6DCPsZMZhVNffyZjMb+
4Q71ckv52DMZlNnHYPwqwvr4jNfYP5zxy43FKsi7P514gH2v3+m0HA4+YyYO
LxrL8TftSRgr2b5t/R8fz2okAJUAAA==

-->

</rfc>

